ctabustracker/__init__.py
ctabustracker/api.py
ctabustracker_v2-1.0.0.dist-info/LICENSE
ctabustracker_v2-1.0.0.dist-info/METADATA
ctabustracker_v2-1.0.0.dist-info/WHEEL
ctabustracker_v2-1.0.0.dist-info/top_level.txt
ctabustracker_v2-1.0.0.dist-info/RECORD
