Metadata-Version: 2.2
Name: ctabustracker-v2
Version: 1.0.0
Summary: A Python 3 wrapper for the CTA Bus Tracker API (v2).
Author-email: "Connor Parnell (github:@cpparnell)" <connorparnell1999@gmail.com>
License: MIT License
Project-URL: Source, https://github.com/yourusername/ctabustracker
Project-URL: Documentation, https://github.com/yourusername/ctabustracker
Keywords: cta,chicago,bus,tracker,api,wrapper
Classifier: Programming Language :: Python :: 3
Classifier: License :: OSI Approved :: MIT License
Classifier: Operating System :: OS Independent
Requires-Python: >=3.7
License-File: LICENSE
Requires-Dist: requests>=2.0
